climy/__init__.py
climy/application.py
climy/command.py
climy/console.py
climy/manager.py
climy/option.py
climy-0.2.1.dist-info/LICENSE
climy-0.2.1.dist-info/METADATA
climy-0.2.1.dist-info/WHEEL
climy-0.2.1.dist-info/RECORD
