Metadata-Version: 2.1
Name: climy
Version: 0.2.1
Summary: Do CLI applications easily.
License: MIT
Author: Manasses Lima
Author-email: manasseslima@gmail.com
Requires-Python: >=3.10,<4.0
Classifier: License :: OSI Approved :: MIT License
Classifier: Programming Language :: Python :: 3
Classifier: Programming Language :: Python :: 3.10
Classifier: Programming Language :: Python :: 3.11
